aipm/.DS_Store
aipm/__init__.py
aipm/config.py
aipm/env.py
aipm/exp.py
aipm/loss.py
aipm/main.py
aipm/model.py
aipm/results/results.txt
aipm/utils.py
aipm-0.1.0.dist-info/METADATA
aipm-0.1.0.dist-info/WHEEL
aipm-0.1.0.dist-info/RECORD
