Metadata-Version: 2.1
Name: aipm
Version: 0.1.0
Summary: AI for Portfolio Management
Author: nvimts
Author-email: scrlk1289@gmail.com
Requires-Python: >=3.11,<4.0
Classifier: Programming Language :: Python :: 3
Classifier: Programming Language :: Python :: 3.11
Classifier: Programming Language :: Python :: 3.12
Classifier: Programming Language :: Python :: 3.13
Requires-Dist: fastparquet (>=2023.10.1,<2024.0.0)
Requires-Dist: pandas (>=2.1.0,<3.0.0)
Requires-Dist: polars (>=0.20.0,<0.21.0)
Requires-Dist: pyarrow (>=13.0.0,<14.0.0)
Requires-Dist: torch (>=2.1.0,<3.0.0)
